LICENSE
README.md
setup.py
real_br/__init__.py
real_br/real_br.py
real_brasileiro.egg-info/PKG-INFO
real_brasileiro.egg-info/SOURCES.txt
real_brasileiro.egg-info/dependency_links.txt
real_brasileiro.egg-info/top_level.txt