Metadata-Version: 2.1
Name: real-brasileiro
Version: 0.2.5
Summary: UNKNOWN
Home-page: https://github.com/MikalROn/Real_br
Author: Daniel Coêlho
Author-email: heromon.9010@gmail.com
License: UNKNOWN
Platform: UNKNOWN
Requires-Python: >=3
License-File: LICENSE
